evv4esm/__init__.py
evv4esm/__main__.py
evv4esm/utils.py
evv4esm/ensembles/__init__.py
evv4esm/ensembles/e3sm.py
evv4esm/ensembles/tools.py
evv4esm/extensions/__init__.py
evv4esm/extensions/ks.bib
evv4esm/extensions/ks.py
evv4esm/extensions/ks_vars.json
evv4esm/extensions/kso.py
evv4esm/extensions/ocean_vars.json
evv4esm/extensions/pg.bib
evv4esm/extensions/pg.py
evv4esm/extensions/tsc.bib
evv4esm/extensions/tsc.py
evv4esm/resources/.gitignore
evv4esm/resources/__init__.py
evv4esm/resources/favicon.ico
evv4esm/resources/index.html
evv4esm/resources/validation.html
evv4esm/resources/css/acknowledgments.css
evv4esm/resources/css/captionjs.min.css
evv4esm/resources/css/jquery-ui.min.css
evv4esm/resources/css/lightbox.min.css
evv4esm/resources/css/livv.css
evv4esm/resources/css/normalize.css
evv4esm/resources/imgs/DOE-BER-logo.png
evv4esm/resources/imgs/DOE-logo.png
evv4esm/resources/imgs/ORNL-logo.png
evv4esm/resources/imgs/background.jpg
evv4esm/resources/imgs/close.png
evv4esm/resources/imgs/icon.svg
evv4esm/resources/imgs/loading.gif
evv4esm/resources/imgs/next.png
evv4esm/resources/imgs/prev.png
evv4esm/resources/js/common.js
evv4esm/resources/js/jquery-ui.min.js
evv4esm/resources/js/jquery.caption.min.js
evv4esm/resources/js/jquery.min.js
evv4esm/resources/js/lightbox.min.js
evv4esm/resources/js/lightbox.min.map
evv4esm-0.5.2.dist-info/LICENSE
evv4esm-0.5.2.dist-info/METADATA
evv4esm-0.5.2.dist-info/WHEEL
evv4esm-0.5.2.dist-info/entry_points.txt
evv4esm-0.5.2.dist-info/top_level.txt
evv4esm-0.5.2.dist-info/RECORD
