Metadata-Version: 2.1
Name: evv4esm
Version: 0.5.2
Summary: Extended verification and validation for earth system models
Author-email: Michael Kelleher <kelleherme@ornl.gov>, "Joseph H. Kennedy" <kennedyjh@ornl.gov>
License: BSD-3-Clause
Project-URL: Homepage, https://github.com/LIVVkit/evv4esm
Classifier: Development Status :: 5 - Production/Stable
Classifier: Intended Audience :: Science/Research
Classifier: Topic :: Scientific/Engineering
Classifier: Topic :: Software Development :: Testing
Classifier: License :: OSI Approved :: BSD License
Classifier: Natural Language :: English
Classifier: Operating System :: OS Independent
Classifier: Programming Language :: Python :: 3
Classifier: Programming Language :: Python :: 3.6
Classifier: Programming Language :: Python :: 3.7
Classifier: Programming Language :: Python :: 3.8
Classifier: Programming Language :: Python :: 3.9
Classifier: Programming Language :: Python :: 3.10
Classifier: Programming Language :: Python :: 3.11
Classifier: Programming Language :: Python :: 3.12
Requires-Python: >=3.6
License-File: LICENSE
Requires-Dist: setuptools
Requires-Dist: six
Requires-Dist: numpy
Requires-Dist: scipy
Requires-Dist: pandas >=2.1.0
Requires-Dist: livvkit >=3.0.1
Requires-Dist: netCDF4
Requires-Dist: matplotlib
Requires-Dist: pybtex >=0.24.0
Requires-Dist: statsmodels >=0.14.0
Provides-Extra: dev
Requires-Dist: modelmimic ; extra == 'dev'
Requires-Dist: ruff ; extra == 'dev'
Requires-Dist: black ; extra == 'dev'
Requires-Dist: isort ; extra == 'dev'
Requires-Dist: pytest ; extra == 'dev'
